ether_dream/__init__.py
ether_dream/ether_dream.py
ether_dream-0.1.1.dist-info/LICENSE
ether_dream-0.1.1.dist-info/METADATA
ether_dream-0.1.1.dist-info/WHEEL
ether_dream-0.1.1.dist-info/top_level.txt
ether_dream-0.1.1.dist-info/RECORD
